{"inkVersion":21,"root":[["^Oh, you startled me! I did not expect to see another climber around. My name's Rita.","\n","ev","str","^Nice to meet you Rita.","/str","/ev",{"*":"0.c-0","flg":20},"ev","str","^I don't care.","/str","/ev",{"*":"0.c-1","flg":20},{"c-0":["^ ",{"->":"met"},"\n",{"->":"0.g-0"},{"#f":5}],"c-1":["\n","^Well that's not too nice! Be on your way then, careful you don't slip! Hmph.","\n",["ev","str","^Say nothing","/str","/ev",{"*":".^.c-0","flg":20},"ev","str","^Sorry, I didn't mean it.","/str","/ev",{"*":".^.c-1","flg":20},{"c-0":["\n",{"->":"0.g-0"},{"#f":5}],"c-1":["\n","^...Alright. The climb took its toll on you didn't it? Anyways,","\n",{"->":"met"},{"->":"0.g-0"},{"#f":5}]}],{"#f":5}],"g-0":["done",{"#f":5}]}],"done",{"met":[["^The wizard said there's all sorts of treasure at the top. Doesn't that sound intriguing?","\n","ev","str","^Can't wait to get my hands on it.","/str","/ev",{"*":".^.c-0","flg":20},"ev","str","^The tower itself is more intriguing.","/str","/ev",{"*":".^.c-1","flg":20},{"c-0":["\n","^If you can beat me to it! ",{"->":"part2"},"\n",{"#f":5}],"c-1":["\n","^Hmm, looking for adventure. I see. I'll give it to you, the sheer scale of this place is pretty intimidating. ",{"->":"part2"},"\n",{"#f":5}]}],{"#f":1}],"part2":[["^Hey, you know what I was thinking? How does that wizard know what's at the top??","\n","^Is it his tower or something? Then he must have the key. Maybe we could just steal it and take the stairs! Would save us a lot of trouble.","\n","ev","str","^Stealing from old men is not my thing","/str","/ev",{"*":".^.c-0","flg":20},"ev","str","^I can get behind that!","/str","/ev",{"*":".^.c-1","flg":20},{"c-0":["\n","^Faint of heart eh? That's fine, I wasn't seriously considering it. ",{"->":"part3"},"\n",{"#f":5}],"c-1":["\n","^Well, I don't really feel like climbing down just yet. I just got here! And it wasn't easy! ",{"->":"part3"},"\n",{"#f":5}]}],{"#f":1}],"part3":["^...","\n","^Take a break here if you want. I'll stay here for a while longer. But don't you get cocky! I'll definetly beat you to the treasure!","\n","done",{"#f":1}],"#f":1}],"listDefs":{}}